[
    {
        "id":0,
        "geolocation": [
            139.73125218853,
            35.6661965145758
        ],
        "name": "Yahoo Japan 11階 男子トイレ",
        "owner": 0,
        "photo": [
            {
                "type": "spherecal",
                "uri": "yj11fmen.jpg",
                "title": "トイレイメージ"
            }
        ],
        "note": "日本のIT界の巨人、誰もが知っているYahoo! Japan社内です。僕のじゃありませんが、勝手に領有権を主張しています。",
        "tags": [
            "IT企業",
            "自動洗浄",
            "ウォシュレット",
            "待ち無し"
        ],
        "public": true,
        "review": [
            {
                "reviewer": 0,
                "title": "手を触れずに流せる贅沢。",
                "note": "さすがのY!J、トイレのUXすら考え抜かれている。そう、洗浄ノブは不衛生なのです。ここにちゃんとコストを掛けて非接触化しているのは非常に好印象。もうヘビロテ決定です。",
                "rate": 5
            }
        ]
    },
    {
        "id":1,
        "geolocation": [
            139.76320008465575,
            35.725186448820935
        ],
        "name": "松尾邸 1F",
        "owner": 1,
        "photo": [],
        "note": "文京区の落ち着きをぐっと凝縮したトイレ。",
        "tags": [
            "民家",
            "男性一人暮らし",
            "洋式"
        ],
        "review": [
            {
                "reviewer": 0,
                "title": "良くも普通、悪くも普通",
                "note": "ふと気づかされる、ウォシュレットが当たり前になっていた生活。1980年代のトイレを思わせるひやりとして感触は、私に忘れていた大切な何かを思い出させます。",
                "rate": 4
            }
        ]
    },
    {
        "id":2,
        "geolocation": [
            139.76320008465575,
            35.725186448820935
        ],
        "name": "[ow;d]鷺ノ宮HQ",
        "owner": 0,
        "photo": [
            {
                "type": "normal",
                "uri": "saginomiyahq.jpg",
                "title": "トイレイメージ"
            }
        ],
        "note": "今ナウなヤングにバカウケ！通は練馬でクソをする。",
        "tags": [
            "集合住宅",
            "男性一人暮らし",
            "洋式",
            "ウォシュレット",
            "オゾン脱臭"
        ],
        "public": true,
        "review": [
            {
                "reviewer": 0,
                "title": "良くも普通、悪くも普通",
                "note": "ふと気づかされる、ウォシュレットが当たり前になっていた生活。1980年代のトイレを思わせるひやりとして感触は、私に忘れていた大切な何かを思い出させます。",
                "rate": 4
            }
        ]
    }
]
